{"index.md":"B22jtIkn","man_chemicaldiffusion.md":"kBPWddHR","man_conductivity.md":"BeOPf4bF","man_contributing.md":"CNIYo13y","man_creeplaws.md":"DgRaKNEP","man_customrheology.md":"BONlt-cX","man_density.md":"CC8MaJ-h","man_elasticity.md":"CkaJnAXm","man_garnet.md":"jCVK8eds","man_geounit.md":"CLufS9qa","man_gravity.md":"DaFxtwFf","man_heatcapacity.md":"jvjIbMcE","man_latentheat.md":"BjY_t_Mb","man_listfunctions.md":"w2Fvnyhb","man_materialparameters.md":"BWly9YCB","man_melt.md":"BTeGiIYA","man_melting.md":"BByLvcl0","man_nondimensionalize.md":"DOKlpSnB","man_olivine.md":"Bono4PHs","man_permeability.md":"DTuZRH2F","man_phasediagrams.md":"BEXa6dJX","man_plasticity.md":"BzWdUjDo","man_plotting.md":"DTzDfUv_","man_radioactiveheating.md":"Rj-SxiMU","man_rutile.md":"C4NJsXc8","man_seismicvelocity.md":"Bu_woa1k","man_shearheating.md":"CF-RT_q7","man_strengthenvelope.md":"1O6m_sie","man_tables.md":"Cct11Epo","man_tasclassification.md":"CKKUafXl","man_viscosity.md":"CX7iX_Ru","man_zirconages.md":"BG-dklH1"}
